fuzzmatch/LICENSE
fuzzmatch/README.MD
fuzzmatch/__init__.py
fuzzmatch/fuzzmatcher.h
fuzzmatch/requirements.txt
fuzzmatch/thirdparty.json
fuzzmatch/uiev.pyx
fuzzmatch/uiev_compile.py
fuzzmatch-0.10.dist-info/LICENSE.rst
fuzzmatch-0.10.dist-info/METADATA
fuzzmatch-0.10.dist-info/WHEEL
fuzzmatch-0.10.dist-info/top_level.txt
fuzzmatch-0.10.dist-info/RECORD
