Metadata-Version: 2.1
Name: fuzzmatch
Version: 0.10
Summary: Very Fast Batch String Matching in Python (Levenshtein, Jaro-Winkler, Hamming) with Zero Cache Misses - written in C++
Home-page: https://github.com/hansalemaos/fuzzmatch
Author: Johannes Fischer
Author-email: aulasparticularesdealemaosp@gmail.com
License: MIT
Keywords: Levenshtein,Jaro-Winkler,Hamming
Classifier: Development Status :: 4 - Beta
Classifier: Programming Language :: Python :: 3 :: Only
Classifier: Programming Language :: Python :: 3.10
Classifier: Topic :: Software Development :: Libraries :: Python Modules
Classifier: Topic :: Utilities
License-File: LICENSE.rst
Requires-Dist: Cython
Requires-Dist: setuptools
